{
  "contest_slug": "congressional-district-3-u-s-representative",
  "reviewed_at": "2026-07-17",
  "verdicts": [
    {
      "candidate": "marie-gluesenkamp-perez",
      "axis": "spending",
      "verdict": "upheld"
    },
    {
      "candidate": "marie-gluesenkamp-perez",
      "axis": "reform",
      "verdict": "upheld"
    },
    {
      "candidate": "marie-gluesenkamp-perez",
      "axis": "healthcare",
      "verdict": "upheld"
    },
    {
      "candidate": "marie-gluesenkamp-perez",
      "axis": "social",
      "verdict": "upheld"
    },
    {
      "candidate": "marie-gluesenkamp-perez",
      "axis": "experience",
      "verdict": "upheld"
    },
    {
      "candidate": "brent-hennrich",
      "axis": "taxes",
      "verdict": "upheld"
    },
    {
      "candidate": "brent-hennrich",
      "axis": "spending",
      "verdict": "upheld"
    },
    {
      "candidate": "brent-hennrich",
      "axis": "reform",
      "verdict": "upheld"
    },
    {
      "candidate": "brent-hennrich",
      "axis": "immigration",
      "verdict": "upheld"
    },
    {
      "candidate": "brent-hennrich",
      "axis": "healthcare",
      "verdict": "upheld"
    },
    {
      "candidate": "brent-hennrich",
      "axis": "defense",
      "verdict": "upheld"
    },
    {
      "candidate": "brent-hennrich",
      "axis": "experience",
      "verdict": "upheld"
    },
    {
      "candidate": "john-p-roco",
      "axis": "immigration",
      "verdict": "upheld"
    },
    {
      "candidate": "john-p-roco",
      "axis": "social",
      "verdict": "upheld"
    },
    {
      "candidate": "john-p-roco",
      "axis": "experience",
      "verdict": "upheld"
    },
    {
      "candidate": "john-saulie-rohman",
      "axis": "spending",
      "verdict": "upheld"
    },
    {
      "candidate": "john-saulie-rohman",
      "axis": "reform",
      "verdict": "upheld"
    },
    {
      "candidate": "john-saulie-rohman",
      "axis": "defense",
      "verdict": "upheld"
    },
    {
      "candidate": "john-saulie-rohman",
      "axis": "experience",
      "verdict": "upheld"
    },
    {
      "candidate": "troy-rasband",
      "axis": "taxes",
      "verdict": "upheld"
    },
    {
      "candidate": "troy-rasband",
      "axis": "spending",
      "verdict": "upheld"
    },
    {
      "candidate": "troy-rasband",
      "axis": "experience",
      "verdict": "upheld"
    },
    {
      "candidate": "john-braun",
      "axis": "taxes",
      "verdict": "upheld"
    },
    {
      "candidate": "john-braun",
      "axis": "spending",
      "verdict": "upheld"
    },
    {
      "candidate": "john-braun",
      "axis": "safety",
      "verdict": "upheld"
    },
    {
      "candidate": "john-braun",
      "axis": "immigration",
      "verdict": "upheld"
    },
    {
      "candidate": "john-braun",
      "axis": "social",
      "verdict": "upheld"
    },
    {
      "candidate": "john-braun",
      "axis": "defense",
      "verdict": "upheld"
    },
    {
      "candidate": "john-braun",
      "axis": "experience",
      "verdict": "upheld"
    },
    {
      "candidate": "antony-barran",
      "axis": "climate",
      "verdict": "upheld"
    },
    {
      "candidate": "antony-barran",
      "axis": "experience",
      "verdict": "upheld"
    },
    {
      "candidate": "austin-braswell",
      "axis": "safety",
      "verdict": "adjust",
      "adjusted_score": 1,
      "adjusted_confidence": "low",
      "note": "Police-accountability emphasis can lean away from enforcement-first, but the dossier documents no prevention, treatment, diversion, housing-first, or non-police response proposal. Direction is indirect and belongs at low confidence."
    },
    {
      "candidate": "austin-braswell",
      "axis": "reform",
      "verdict": "upheld"
    },
    {
      "candidate": "austin-braswell",
      "axis": "immigration",
      "verdict": "upheld"
    },
    {
      "candidate": "austin-braswell",
      "axis": "tech",
      "verdict": "upheld"
    },
    {
      "candidate": "austin-braswell",
      "axis": "defense",
      "verdict": "upheld"
    },
    {
      "candidate": "austin-braswell",
      "axis": "experience",
      "verdict": "upheld"
    },
    {
      "candidate": "lawrence-kellogg",
      "axis": "taxes",
      "verdict": "upheld"
    },
    {
      "candidate": "lawrence-kellogg",
      "axis": "immigration",
      "verdict": "upheld"
    },
    {
      "candidate": "lawrence-kellogg",
      "axis": "reform",
      "verdict": "adjust",
      "adjusted_score": 1,
      "adjusted_confidence": "low",
      "note": "Transparency and voter access suggest reform, but the dossier gives no campaign-money, term-limit, voting-system, or direct-democracy proposal matching the rubric's named structural examples."
    },
    {
      "candidate": "lawrence-kellogg",
      "axis": "experience",
      "verdict": "upheld"
    }
  ],
  "missing": []
}
