{
  "derived_from": [
    "data/washington-state/counties/douglas/interim/app-contests.json"
  ],
  "script": "pipeline/normalize_research_inputs.py",
  "contests": [
    {
      "category": "Federal",
      "office": "U.S. Representative",
      "district": "Congressional District 4",
      "slug": "douglas-congressional-district-4-u-s-representative",
      "candidates": [
        {
          "slug": "jacek-jack-kobiesa",
          "name": "Jacek \"Jack\" Kobiesa",
          "party_preference": "States No Party Preference"
        },
        {
          "slug": "amanda-mckinney",
          "name": "Amanda McKinney",
          "party_preference": "Prefers Republican Party"
        },
        {
          "slug": "john-duresky",
          "name": "John Duresky",
          "party_preference": "Prefers Democratic Party"
        },
        {
          "slug": "john-c-hughs",
          "name": "John C. Hughs",
          "party_preference": "Prefers Republican Party"
        },
        {
          "slug": "favian-valencia",
          "name": "Favian Valencia",
          "party_preference": "Prefers Independent Party"
        },
        {
          "slug": "jerrod-sessler",
          "name": "Jerrod Sessler",
          "party_preference": "Prefers Republican Party"
        },
        {
          "slug": "devin-poore",
          "name": "Devin Poore",
          "party_preference": "Prefers Cascade Party"
        },
        {
          "slug": "ken-vaz",
          "name": "Ken Vaz",
          "party_preference": "Prefers Republican Party"
        },
        {
          "slug": "zac-rossi",
          "name": "Zac Rossi",
          "party_preference": "States No Party Preference"
        },
        {
          "slug": "elpidia-saavedra",
          "name": "Elpidia Saavedra",
          "party_preference": "Prefers Republican Party"
        },
        {
          "slug": "matt-boehnke",
          "name": "Matt Boehnke",
          "party_preference": "Prefers Republican Party"
        }
      ]
    },
    {
      "category": "Federal",
      "office": "U.S. Representative",
      "district": "Congressional District 8",
      "slug": "douglas-congressional-district-8-u-s-representative",
      "candidates": [
        {
          "slug": "kim-schrier",
          "name": "Kim Schrier",
          "party_preference": "Prefers Democratic Party"
        },
        {
          "slug": "trinh-ha",
          "name": "Trinh Ha",
          "party_preference": "Prefers Republican Party"
        },
        {
          "slug": "spencer-meline",
          "name": "Spencer Meline",
          "party_preference": "Prefers Republican Party"
        },
        {
          "slug": "keith-arnold",
          "name": "Keith Arnold",
          "party_preference": "Prefers Democratic Party"
        },
        {
          "slug": "andres-valleza",
          "name": "Andres Valleza",
          "party_preference": "Prefers Republican Party"
        },
        {
          "slug": "bob-hagglund",
          "name": "Bob Hagglund",
          "party_preference": "Prefers Republican Party"
        }
      ]
    },
    {
      "category": "State",
      "office": "State Senator",
      "district": "Legislative District 7",
      "slug": "douglas-legislative-district-7-state-senator",
      "candidates": [
        {
          "slug": "shelly-short",
          "name": "Shelly Short",
          "party_preference": "Prefers Republican Party"
        },
        {
          "slug": "ronald-l-mccoy",
          "name": "Ronald L McCoy",
          "party_preference": "Prefers Independent Party"
        },
        {
          "slug": "brandon-ray-medina",
          "name": "Brandon Ray Medina",
          "party_preference": "Prefers Republican Party"
        },
        {
          "slug": "david-swoap",
          "name": "David Swoap",
          "party_preference": "Prefers Republican Party"
        }
      ]
    },
    {
      "category": "State",
      "office": "State Representative Pos. 1",
      "district": "Legislative District 7",
      "slug": "douglas-legislative-district-7-state-representative-pos-1",
      "candidates": [
        {
          "slug": "andrew-engell",
          "name": "Andrew Engell",
          "party_preference": "Prefers Republican Party"
        }
      ]
    },
    {
      "category": "State",
      "office": "State Representative Pos. 2",
      "district": "Legislative District 7",
      "slug": "douglas-legislative-district-7-state-representative-pos-2",
      "candidates": [
        {
          "slug": "hunter-abell",
          "name": "Hunter Abell",
          "party_preference": "Prefers Republican Party"
        }
      ]
    },
    {
      "category": "State",
      "office": "State Senator",
      "district": "Legislative District 13",
      "slug": "douglas-legislative-district-13-state-senator",
      "candidates": [
        {
          "slug": "alex-ybarra",
          "name": "Alex Ybarra",
          "party_preference": "Prefers Republican Party"
        }
      ]
    },
    {
      "category": "State",
      "office": "State Representative Pos. 1",
      "district": "Legislative District 13",
      "slug": "douglas-legislative-district-13-state-representative-pos-1",
      "candidates": [
        {
          "slug": "tom-dent",
          "name": "Tom Dent",
          "party_preference": "Prefers Republican Party"
        },
        {
          "slug": "juan-jerry-garcia",
          "name": "Juan \"Jerry\" Garcia",
          "party_preference": "Prefers Democratic Party"
        }
      ]
    },
    {
      "category": "State",
      "office": "State Representative Pos. 2",
      "district": "Legislative District 13",
      "slug": "douglas-legislative-district-13-state-representative-pos-2",
      "candidates": [
        {
          "slug": "deanna-martinez",
          "name": "Deanna Martinez",
          "party_preference": "Prefers Republican Party"
        },
        {
          "slug": "joshua-thompson",
          "name": "Joshua Thompson",
          "party_preference": "Prefers Republican Party"
        },
        {
          "slug": "don-myers",
          "name": "Don Myers",
          "party_preference": "Prefers Republican Party"
        }
      ]
    },
    {
      "category": "County",
      "office": "Assessor",
      "district": "Douglas County",
      "slug": "douglas-douglas-county-assessor",
      "candidates": [
        {
          "slug": "jim-ruud",
          "name": "Jim Ruud",
          "party_preference": "Prefers Republican Party"
        }
      ]
    },
    {
      "category": "County",
      "office": "Auditor",
      "district": "Douglas County",
      "slug": "douglas-douglas-county-auditor",
      "candidates": [
        {
          "slug": "thad-duvall",
          "name": "Thad Duvall",
          "party_preference": "Prefers Nonpartisan Party"
        }
      ]
    },
    {
      "category": "County",
      "office": "Clerk of Superior Court",
      "district": "Douglas County",
      "slug": "douglas-douglas-county-clerk-of-superior-court",
      "candidates": [
        {
          "slug": "jenn-biggar",
          "name": "Jenn Biggar",
          "party_preference": "Prefers Republican Party"
        },
        {
          "slug": "andrea-jester",
          "name": "Andrea Jester",
          "party_preference": "Prefers Republican Party"
        }
      ]
    },
    {
      "category": "County",
      "office": "Commissioner District No. 3",
      "district": "Douglas County Commissioner District 3",
      "slug": "douglas-douglas-county-commissioner-district-3-commissioner-district-no-3",
      "candidates": [
        {
          "slug": "marc-s-straub",
          "name": "MARC S. STRAUB",
          "party_preference": "Prefers Republican Party"
        },
        {
          "slug": "michael-s-lesky",
          "name": "Michael S. Lesky",
          "party_preference": "Prefers Independent Party"
        }
      ]
    },
    {
      "category": "County",
      "office": "Coroner",
      "district": "Douglas County",
      "slug": "douglas-douglas-county-coroner",
      "candidates": [
        {
          "slug": "tanner-bateman",
          "name": "Tanner Bateman",
          "party_preference": "Prefers Republican Party"
        }
      ]
    },
    {
      "category": "County",
      "office": "Prosecuting Attorney",
      "district": "Douglas County",
      "slug": "douglas-douglas-county-prosecuting-attorney",
      "candidates": [
        {
          "slug": "sean-p-lewis",
          "name": "Sean P. Lewis",
          "party_preference": "Prefers Republican Party"
        }
      ]
    },
    {
      "category": "County",
      "office": "Sheriff",
      "district": "Douglas County",
      "slug": "douglas-douglas-county-sheriff",
      "candidates": [
        {
          "slug": "tyler-i-caille",
          "name": "Tyler I. Caille",
          "party_preference": "Prefers Republican Party"
        },
        {
          "slug": "adam-musgrove",
          "name": "Adam Musgrove",
          "party_preference": "Prefers Republican Party"
        },
        {
          "slug": "kieth-a-siebert",
          "name": "Kieth A. Siebert",
          "party_preference": "Prefers Republican Party"
        }
      ]
    },
    {
      "category": "County",
      "office": "Treasurer",
      "district": "Douglas County",
      "slug": "douglas-douglas-county-treasurer",
      "candidates": [
        {
          "slug": "felisha-l-rosales",
          "name": "Felisha L. Rosales",
          "party_preference": "Prefers Republican Party"
        }
      ]
    }
  ]
}
