{
  "contest_slug": "pierce-pierce-county-council-district-1-county-councilmember",
  "reviewed_at": "2026-07-17",
  "verdicts": [
    {"candidate": "jerome-o-leary", "axis": "spending", "verdict": "upheld"},
    {"candidate": "jerome-o-leary", "axis": "experience", "verdict": "upheld"},
    {"candidate": "terrance-mayers", "axis": "spending", "verdict": "upheld"},
    {"candidate": "terrance-mayers", "axis": "safety", "verdict": "upheld"},
    {"candidate": "terrance-mayers", "axis": "experience", "verdict": "upheld"},
    {"candidate": "kenneth-king", "axis": "spending", "verdict": "upheld"},
    {"candidate": "kenneth-king", "axis": "safety", "verdict": "adjust", "adjusted_score": 2, "adjusted_confidence": "medium", "note": "The +2 direction and magnitude are supported by his explicit voluntary-stabilization, behavioral-health-diversion, and coordinated-services approach [S2]. Confidence should be medium because the position rests on a single campaign source; cited S3 verifies board participation but does not independently corroborate the safety posture."},
    {"candidate": "kenneth-king", "axis": "experience", "verdict": "upheld"},
    {"candidate": "kelsey-barrans", "axis": "spending", "verdict": "upheld"},
    {"candidate": "kelsey-barrans", "axis": "experience", "verdict": "upheld"}
  ],
  "missing": []
}
